congressclient/__init__.py
congressclient/exceptions.py
congressclient/i18n.py
congressclient/common/__init__.py
congressclient/common/parseractions.py
congressclient/common/utils.py
congressclient/osc/__init__.py
congressclient/osc/osc_plugin.py
congressclient/osc/v1/__init__.py
congressclient/osc/v1/api_versions.py
congressclient/osc/v1/datasource.py
congressclient/osc/v1/driver.py
congressclient/osc/v1/policy.py
congressclient/tests/__init__.py
congressclient/tests/base.py
congressclient/tests/common.py
congressclient/tests/fakes.py
congressclient/tests/utils.py
congressclient/tests/v1/__init__.py
congressclient/tests/v1/test_api_versions.py
congressclient/tests/v1/test_datasource.py
congressclient/tests/v1/test_drivers.py
congressclient/tests/v1/test_policy.py
congressclient/tests/v1/test_policy_file.yaml
congressclient/v1/__init__.py
congressclient/v1/client.py
python_congressclient-2.0.1.dist-info/AUTHORS
python_congressclient-2.0.1.dist-info/LICENSE
python_congressclient-2.0.1.dist-info/METADATA
python_congressclient-2.0.1.dist-info/WHEEL
python_congressclient-2.0.1.dist-info/entry_points.txt
python_congressclient-2.0.1.dist-info/pbr.json
python_congressclient-2.0.1.dist-info/top_level.txt
python_congressclient-2.0.1.dist-info/RECORD
