Metadata-Version: 2.1
Name: python-congressclient
Version: 2.0.1
Summary: Client for Congress
Home-page: https://docs.openstack.org/python-congressclient/latest/
Author: OpenStack
Author-email: openstack-discuss@lists.openstack.org
License: UNKNOWN
Platform: UNKNOWN
Classifier: Environment :: OpenStack
Classifier: Intended Audience :: Information Technology
Classifier: Intended Audience :: System Administrators
Classifier: License :: OSI Approved :: Apache Software License
Classifier: Operating System :: POSIX :: Linux
Classifier: Programming Language :: Python
Classifier: Programming Language :: Python :: 3
Classifier: Programming Language :: Python :: 3.6
Classifier: Programming Language :: Python :: 3.7
Requires-Dist: pbr (!=2.1.0,>=2.0.0)
Requires-Dist: Babel (!=2.4.0,>=2.3.4)
Requires-Dist: cliff (!=2.9.0,>=2.8.0)
Requires-Dist: keystoneauth1 (>=3.4.0)
Requires-Dist: oslo.i18n (>=3.15.3)
Requires-Dist: oslo.log (>=3.36.0)
Requires-Dist: oslo.serialization (!=2.19.1,>=2.18.0)
Requires-Dist: six (>=1.10.0)
